tblastn_wrapper/__init__.py
tblastn_wrapper/__main__.py
tblastn_wrapper/rhymes/ Human
.fa
tblastn_wrapper/rhymes/ Plymouth Gran Fury 
.fa
tblastn_wrapper/rhymes/', line) != None):
.py
tblastn_wrapper/rhymes/', line) == None and line != None):
.py
tblastn_wrapper/rhymes/>.py
tblastn_wrapper/rhymes/Human
.fa
tblastn_wrapper/rhymes/Human.fa
tblastn_wrapper/rhymes/Plymouth Gran Fury 
.fa
tblastn_wrapper/rhymes/Plymouth Gran Fury.fa
tblastn_wrapper/rhymes/Plymouth_Gran_Fury.fa
tblastn_wrapper/rhymes/Seal
.fa
tblastn_wrapper/rhymes/Seal.fa
tblastn_wrapper/rhymes/practice.py
tblastn_wrapper/rhymes/random.fa
tblastn_wrapper/wrapper_function.py
tblastn_wrapper-0.1.15.dist-info/entry_points.txt
tblastn_wrapper-0.1.15.dist-info/LICENSE
tblastn_wrapper-0.1.15.dist-info/WHEEL
tblastn_wrapper-0.1.15.dist-info/METADATA
tblastn_wrapper-0.1.15.dist-info/RECORD
